<?xml version="1.0" encoding="utf-8"?>
<products>
  <product>
    <title>Pola śmierci</title>
    <format>MOBI</format>
    <security/>
    <price>7.20</price>
    <isbn>978-83-63598-93-8</isbn>
    <coverId>145445</coverId>
    <authors>Marek Ścieszek</authors>
    <url>http://virtualo.pl/pola_smierci/i128988/</url>
    <description>
      <p> </p>
      <p>Na początku pola śmierci miały być tylko interesem, nieludzkim, bluźnierczym, ale prowadzącym do łatwego zarobku. W świecie fantasy w sprawy zwykłych ludzi lubią się jednak mieszać siły nadprzyrodzone. Przy czym nie sposób jednoznacznie stwierdzić, w którym miejscu przebiega granica porządku. Nic nie jest albo czarne, albo białe. W szarościach niknie pewność co do istoty zła. Zamęt, mroczna siła stojąca w opozycji do Natury, powołuje do życia Bestię, która dzieło ludzi postanawia kontynuować na własnych warunkach. Konflikt jest nieunikniony. Jaką rolę odegra w nim człowiek zamknięty w klatce? Po której stronie opowie się tajemniczy Zakon Rycerzy Smoka? A przede wszystkim kto w tym świecie zasługuje na miano prawdziwej bestii: dziecię Zamętu czy sam człowiek? Odpowiedzi należy szukać na bezkresnych Polach śmierci...</p>
    </description>
    <descriptionShort>Na początku pola śmierci miały być tylko interesem, nieludzkim, bluźnierczym, ale prowadzącym do łatwego zarobku. W świecie fantasy w sprawy zwykłych ludzi lubią się jednak mieszać siły nadprzyrodzone...</descriptionShort>
    <rating>0</rating>
  </product>
  <product>
    <title>Kochanek z piekła rodem</title>
    <format>MOBI</format>
    <security>WM</security>
    <price>22.90</price>
    <isbn>978-83-7551-356-1</isbn>
    <coverId>141309</coverId>
    <authors>Sabrina Jeffries</authors>
    <url>http://virtualo.pl/kochanek_piekla_rodem/i128989/</url>
    <description>
      <p>Lord Jarret Sharpe, nałogowy karciarz i kobieciarz, skłonny jest raczej  poprowadzić rodzinny browar, niż się ożenić. A taki bezlitosny warunek  uzyskania dostępu do rodzinnego majątku stawia przed nim i jego  rodzeństwem babka. Wszyscy muszą w ciągu roku zmienić swój stan cywilny.  Jeśli lordowi Jarretowi uda się zwiększyć dochody nieźle prosperującego  browaru  on i rodzeństwo będą mieli utrzymanie, nawet jeśli nie zdołają  spełnić warunku babki. Nieoczekiwanie pojawia się intrygująca panna  Lake. Potrzebuje pomocy w sprzedaży doskonałego piwa, które według jej  receptury robione jest w małym i podupadającym browarze jej brata. Musi  ratować browar sama, bo brat jest alkoholikiem. Zlekceważona, postanawia  zagrać na słabości hazardzisty. Proponuje grę w karty o dość niezwykłą  stawkę. Jeśli lord Jarret przegra, będzie musiał zgodzić się na wspólne  przedsięwzięcie, jeśli zaś wygra, ona ... ofiaruje mu swoje ciało. Czy  człowiekowi honoru wolno jest przyjąć taki zakład? Panna stawia na szali  bezcenną reputację, a więc całe swoje życie. Jakie okoliczności kryją  się za tak desperackim krokiem? I jakiego jeszcze piwa nawarzą namiętni  gracze?</p>
    </description>
    <descriptionShort>Książka z cyklu Diablęta z Hallstead Hall 
Lord Jarret Sharpe, nałogowy karciarz i kobieciarz, skłonny jest raczej poprowadzić rodzinny browar, niż się ożenić.....</descriptionShort>
    <rating>0</rating>
  </product>
  <product>
    <title>Poradnik działkowca Porady dla właścicieli działek</title>
    <format>EPUB</format>
    <security>WM</security>
    <price>28.00</price>
    <isbn>978-83-7859-152-8</isbn>
    <coverId>143440</coverId>
    <authors>Krzysztof Lewandowski</authors>
    <url>http://virtualo.pl/poradnik_dzialkowca_porady_dla_wlascicieli_dzialek/i128990/</url>
    <description>
      <p>Książka zawiera praktyczne porady dotyczące zakupu i zagospodarowania działek.<br/><br/>Kupowałem ziemię, sprzedawałem działki, wiem z własnego doświadczenia jak na pozór błahe sprawy mogą zagmatwać i zniechęcić do zakupu wymarzonej ziemi.<br/><br/>Kupno działki to inwestycja na przyszłość. Ziemia była i jest inwestycją, która może być przekazywana przez następne pokolenia. Brzmi to pompatycznie, ale ziemia to nasza oaza, dom wybudowany na naszej ziemi to duma i radość.<br/><br/>Treści zawarte w książce przedstawiają krok po kroku działania związane z zakupem, praktyczne wskazówki i porady w zagospodarowaniu działek. Przedstawię rozwiązania, z którymi każdy właściciel działki się boryka, zaczynając od ogrodzenia, tworzenia ścieżek i murków oporowych, kończąc na tworzeniu samego ogrodu tzn. plantacji roślin (kwiatów, drzew, trawników, warzyw).<br/><br/>W książce pojawią się również dodatkowe pomysły które mogą zbogacić działkę z punktu widzenia praktycznego i rekreacyjnego, pokaże jak można założyć ognisko, zrobić zbiorniki wodne, praktycznie przechowywać narzędzia. Przedstawiam zdjęcia rabat z Francji.<br/><br/><br/><br/></p>
    </description>
    <descriptionShort>Książka zawiera praktyczne porady dotyczące zakupu i zagospodarowania działek.</descriptionShort>
    <rating>0</rating>
  </product>
  <product>
    <title>Rodzicu, trenerze - to warto wiedzieć</title>
    <format>MP3</format>
    <security>WM</security>
    <price>22.90</price>
    <isbn>978-83-7902-036-2</isbn>
    <coverId>144136</coverId>
    <authors>Andrzej Olczyk, Anna Mucha, Agnieszka Fornalczyk</authors>
    <url>http://virtualo.pl/rodzicu_trenerze_to_warto_wiedziec/i128991/</url>
    <description>
      <p> </p>
      <p>Marzeniem każdego człowieka jest osiągnięcie sukcesu osobistego oraz zawodowego, własnego i swoich bliskich.</p>
      <p>Rodzicu – Trenerze! Masz wreszcie okazję to urzeczywistnić. Sukces Twoich podopiecznych – jest Twoim sukcesem. To właśnie Ty musisz rozbudzić w nich poczucie własnej wartości i godności, sprawić, że młody sportowiec będzie czuł się pewny siebie, będzie przekonany, że jest na właściwej drodze.</p>
      <p>Rodzicu – Trenerze! Jesteś odpowiedzialny za jego potencjał fizyczny i psychiczny. Ty, aby zyskać miano perfekcjonisty musisz wzmocnić swoje dziecko – sportowca. Możesz być jego drogowskazem. Tylko pozytywny komunikat z Twojej strony może zapewnić sukces Tobie i Twojemu podopiecznemu.</p>
      <p>W skład albumu: Rodzicu – Trenerze, to warto wiedzieć, wchodzą następujące audiobooki:</p>
      <p><span><span>1.<span> </span></span></span>Jak zachęcać dziecko bez presji,</p>
      <p><span><span>2.<span> </span></span></span>Wspieranie rozwoju młodych sportowców w dyscyplinach indywidualnych – 10 porad dla rodziców,</p>
      <p><span><span>3.<span> </span></span></span>Głównie wygrana czy radość z gry w piłkę nożną,</p>
      <p><span><span>4.<span> </span></span></span>Odpowiednia komunikacja i pozytywny wpływ rodzica na rozwój swojego dziecka,</p>
      <p><span><span>5.<span> </span></span></span>Przyłapuj swojego sportowca na tym co zrobi dobrze,</p>
      <p><span><span>6.<span> </span></span></span>Pozytywny sposób myślenia trenera a oddziaływanie na zespół,</p>
      <p><span><span>7.<span> </span></span></span>Autorefleksja i doskonalenie pracy trenera, część pierwsza,</p>
      <p><span><span>8.<span> </span></span></span>Optymalne wykorzystanie talentów i zasobów młodych zawodników,</p>
      <p><span><span>9.<span> </span></span></span>Szansa na podniesienie efektywności swoich młodych sportowców,</p>
      <p><span><span>10.<span> </span></span></span>Biografia Joanny Jędrzejczyk.</p>
      <p>Dzięki tym audiobookom usłyszysz jak być trenerem nie tylko ciała, ale również umysłu, a także, co musisz wiedzieć, aby Twoi sportowcy odpowiednio wykorzystali swój talent.</p>
    </description>
    <descriptionShort>Marzeniem każdego człowieka jest osiągnięcie sukcesu osobistego oraz zawodowego, własnego i swoich bliskich.</descriptionShort>
    <rating>0</rating>
  </product>
  <product>
    <title>Gryź trawę - Michał Żewłakow</title>
    <format>MP3</format>
    <security>WM</security>
    <price>22.90</price>
    <isbn>978-83-7902-032-4</isbn>
    <coverId>144137</coverId>
    <authors>Iwona Haba, Anna Mucha, Andrzej Olczyk</authors>
    <url>http://virtualo.pl/gryz_trawe_michal_zewlakow/i128992/</url>
    <description>
      <p> </p>
      <p> </p>
      <p>Ten trening daje Ci nieźle w kość. Jesteś spocony, zmieniasz kolejną koszulkę, trener na Ciebie krzyczy, w dodatku pada deszcz, nie wyszło Ci kolejne podanie, zastanawiasz się co robić, za chwilę wybuchniesz, masz dość…</p>
      <p>Musisz skupić się na uwagach trenera, już najwyższy czas zacząć ćwiczyć myśli. Zapomnij o złości i pocie, który spływa Ci po plecach. Skoncentruj się na tym co jest ‘’tu i teraz’’. Jesteś przecież jak Michał Żewłakow – zawodowcem, profesjonalistą w panowaniu nad sobą. Wiesz jak zachować się w zespole gdy wygrywacie lub przegrywacie. To, co dzieje się na boisku, znajduje się pod Twoją kontrolą.</p>
      <p>Michał Żewłakow poleca album składający się z jedenastu audiobooków:</p>
      <p><span><span>1.<span> </span></span></span>Ustawiczna praca zawodowego piłkarza nad koncentracją,</p>
      <p><span><span>2.<span> </span></span></span>Trenowanie sposobu myślenia przez zawodowego piłkarza,</p>
      <p><span><span>3.<span> </span></span></span>Motywacja przed meczem,</p>
      <p><span><span>4.<span> </span></span></span>Motywacja w przerwie kiedy przegrywacie,</p>
      <p><span><span>5.<span> </span></span></span>Motywacja w przerwie kiedy wygrywacie,</p>
      <p><span><span>6.<span> </span></span></span>Motywacja po wygranej,</p>
      <p><span><span>7.<span> </span></span></span>Motywacja po przegranej,</p>
      <p><span><span>8.<span> </span></span></span>Pomóż sobie wrócić na boisko,</p>
      <p><span><span>9.<span> </span></span></span>Twoja pewność siebie – co jej szkodzi a co ją wspiera i buduje,</p>
      <p><span><span>10.<span> </span></span></span>Pomóż sobie otworzyć nowe drzwi,</p>
      <p><span><span>11.<span> </span></span></span>‘’Mentalność zwycięzcy’’ – biografia Michała Żewłakowa</p>
      <p>Mamy nadzieję, że dzięki nim będziesz wiedział jak walczyć nie tylko o piłkę, ale również jak walczyć z samym sobą. Jak być najlepszym na boisku, jak współpracować z kolegami z zespołu, trenerem oraz z sędzią.<span> </span></p>
    </description>
    <descriptionShort>Ten trening daje Ci nieźle w kość. Jesteś spocony, zmieniasz kolejną koszulkę, trener na Ciebie krzyczy, w dodatku pada deszcz, nie wyszło Ci kolejne podanie, zastanawiasz się co robić, za chwilę wybuchniesz, masz dość…</descriptionShort>
    <rating>0</rating>
  </product>
  <product>
    <title>Artur Boruc Radzi</title>
    <format>MP3</format>
    <security>WM</security>
    <price>22.90</price>
    <isbn>978-83-7902-020-1</isbn>
    <coverId>144319</coverId>
    <authors>Iwona Haba, Dorota Świetlicka, Anna Mucha</authors>
    <url>http://virtualo.pl/artur_boruc_radzi/i128993/</url>
    <description>
      <p>Artur Boruc może Cię nauczyć wielu postaw. Zapewne wielu z Was chciałoby posiadać jego cechy. Do tych najbardziej wyrazistych należą: dystans do samego siebie , spektakularne zachowania na boisku (które pamięta każdy), niesamowita ambicja. Ten znakomity bramkarz nie byłby dzisiaj tym, kim jest gdyby nie jego wiara we własne nieograniczone możliwości i umiejętności. Ty też – tak jak on – masz szansę nauczyć się pewności siebie. Zainwestuj nie tylko w strój sportowy, dobre buty ale przede wszystkim w swój umysł. Śmiało! Podejmij to wyzwanie, usuń wszelkie przeszkody – szkodniki które Cię dekoncentrują, przeszkadzają w byciu tym, kim chcesz być na boisku.</p>
      <p>W tym albumie składającym się z sześciu audiobooków:</p>
      <p><span><span>1.<span> </span></span></span>Motywujący wpływ dialogu wewnętrznego,</p>
      <p><span><span>2.<span> </span></span></span>Twoja pewność siebie – co jej szkodzi a co ją wspiera i buduje,</p>
      <p><span><span>3.<span> </span></span></span>Dobre nawyki – dobre praktyki,</p>
      <p><span><span>4.<span> </span></span></span>Bramkarz i rozmowa z samym sobą,</p>
      <p><span><span>5.<span> </span></span></span>Podładowanie nastawienia bramkarza na etapie treningu,</p>
      <p><span><span>6.<span> </span></span></span>Teraźniejszość skarbem bramkarza.</p>
      <p><span> </span>Artur Boruc może pomóc Ci ochronić Twój umysł przed napływem negatywnych myśli. Może rozbudzić w Tobie zaufanie do własnych pragnień i celów. Jeśli uda Ci się skorzystać z tych porad, wytrwać w ich realizacji, masz szansę realizować się, a wiec być… szczęśliwym człowiekiem.</p>
    </description>
    <descriptionShort>Artur Boruc może Cię nauczyć wielu postaw. Zapewne wielu z Was chciałoby posiadać jego cechy. Do tych najbardziej wyrazistych należą: dystans do samego siebie , spektakularne zachowania na boisku (które pamięta każdy), niesamowita ambicja.</descriptionShort>
    <rating>0</rating>
  </product>
  <product>
    <title>Co masz w głowie to masz w mięśniach</title>
    <format>MP3</format>
    <security>WM</security>
    <price>22.90</price>
    <isbn>978-83-7902-024-9</isbn>
    <coverId>144320</coverId>
    <authors>Iwona Haba, Anna Mucha, Łukasz Bińkowski</authors>
    <url>http://virtualo.pl/co_masz_glowie_to_masz_miesniach/i128994/</url>
    <description>
      <p>Aktywny, żywy, pełen werwy to słowa, które określają każdego sportowca. Jego sprawność fizyczną, a także umysłową. Zgodnie zresztą z zasadą: ‘’Co masz w głowie to masz w mięśniach’’. Praktycznym dowodem prawdziwości tej tezy może być Marcin Żewłakow. Jego biografia może uświadomić każdemu piłkarzowi, że motywacja jest podstawą wszelkiego wysiłku i aktywności sportowca, podnosi jego własną samoocenę. Może uwrażliwić i pozwolić skupić się tylko na tym, co ważne w grze, na boisku, a wyeliminować to, czym nie warto zawracać sobie głowy.</p>
      <p>W tym albumie składającym się z dziewięciu audiobooków, przewodnikiem po krainie motywacji będzie Marcin Żewłakow:</p>
      <p><span><span>1.<span> </span></span></span>Wzmacnianie koncentracji,</p>
      <p><span><span>2.<span> </span></span></span>Motywacja przed meczem,</p>
      <p><span><span>3.<span> </span></span></span>Motywacja w przerwie kiedy przegrywacie,</p>
      <p><span><span>4.<span> </span></span></span>Motywacja w przerwie kiedy wygrywacie,</p>
      <p><span><span>5.<span> </span></span></span>Motywacja po wygranej,</p>
      <p><span><span>6.<span> </span></span></span>Motywacja po przegranej,</p>
      <p><span><span>7.<span> </span></span></span>Pierwsze porażki i jak sobie z nimi radzić,</p>
      <p><span><span>8.<span> </span></span></span>Przekuj złość w zawziętość,</p>
      <p><span><span>9.<span> </span></span></span>‘’Moja filozofia zwycięstwa’’ – biografia Marcina Żewłakowa.</p>
      <p><span> </span>Masz szansę dostać niezłego kopa w dążeniu do celu. Masz szansę pokonać porażkę, a złość przekuć w zawziętość!</p>
      <p> </p>
    </description>
    <descriptionShort>Aktywny, żywy, pełen werwy to słowa, które określają każdego sportowca. Jego sprawność fizyczną, a także umysłową. Zgodnie zresztą z zasadą: ‘’Co masz w głowie to masz w mięśniach’’.</descriptionShort>
    <rating>0</rating>
  </product>
  <product>
    <title>Bądź jak Marcin Gortat</title>
    <format>MP3</format>
    <security>WM</security>
    <price>22.90</price>
    <isbn>978-83-7902-028-7</isbn>
    <coverId>144324</coverId>
    <authors>Łukasz Bińkowski, Anna Mucha, Andrzej Olczyk</authors>
    <url>http://virtualo.pl/badz_jak_marcin_gortat/i128995/</url>
    <description>
      <p> </p>
      <p> </p>
      <p>Marcin Gortat to gwiazda koszykówki. Ale to nie wzrost – 2,14cm uczynił z niego mistrza i sprawił, że jest jednym z najlepszych koszykarzy. To świetna kondycja psychiczna pozwala mu błyszczeć. Ten wirtuoz sportu stoczył niejedną walkę z samym sobą. Być może przyświecała mu zasada Aldousa Huxleya, który twierdził, że po porażce należy robić to, co robią dzieci, to znaczy podnieść się. Ta myśl motywowała go gry jego i cały zespół. Potraktuj porażki jak epizody, które prowadzą do sukcesu, gdyż dzięki nim zdobywasz doświadczenie. Wysłuchaj albumu w skład którego wchodzi osiem audiobooków:</p>
      <p><span><span>1.<span> </span></span></span>Codzienna praca nad pewnością siebie,</p>
      <p><span><span>2.<span> </span></span></span>Postawa mentalna przed meczem,</p>
      <p><span><span>3.<span> </span></span></span>Postawa mentalna w przerwie kiedy przegrywacie,</p>
      <p><span><span>4.<span> </span></span></span>Postawa mentalna w przerwie kiedy wygrywacie,</p>
      <p><span><span>5.<span> </span></span></span>Postawa mentalna po wygranym meczu,</p>
      <p><span><span>6.<span> </span></span></span>Co warto zrobić po wygranej w koszykówce,</p>
      <p><span><span>7.<span> </span></span></span>Wzmacnianie koncentracji podczas treningu,</p>
      <p><span><span>8.<span> </span></span></span>‘’Moja Walka’’ – biografia Marcina Gortata.</p>
      <p>Być może zrozumiesz, że sens nadaje gra - walka do końca. Może zrozumiesz, że nie ma straconych piłek. Właśnie w takich momentach przeciwnik wystawia Cię na próbę. Uwolnij swój talent i cały potencjał. Właśnie wtedy możesz pokazać swój profesjonalizm.</p>
      <p> </p>
    </description>
    <descriptionShort>Marcin Gortat to gwiazda koszykówki. Ale to nie wzrost – 2,14cm uczynił z niego mistrza i sprawił, że jest jednym z najlepszych koszykarzy. To świetna kondycja psychiczna pozwala mu błyszczeć.</descriptionShort>
    <rating>0</rating>
  </product>
  <product>
    <title>Zombie atakują ! Zarządzanie ryzykiem po prostu.</title>
    <format>EPUB</format>
    <security>WM</security>
    <price>23.00</price>
    <isbn>978-83-272-3927-3</isbn>
    <coverId>144773</coverId>
    <authors>Dr Jerzy Podlewski</authors>
    <url>http://virtualo.pl/zombie_atakuja_zarzadzanie_ryzykiem_po_prostu/i128996/</url>
    <description>
      <p>Jaki apetyt na ryzyko miał Czerwony Kapturek ? Dlaczego firmy bankrutują, a ich menadżerowie nie piszą o tym książek?  Czy równouprawnienie zwiększa ryzyko w biznesie ?  Jak profesjonalnie przygotować się na nadejście Żywych Trupów ?</p>
      <p>
        <span>To niektóre, z wielu zaskakujących pytań, na które równie nieoczekiwane odpowiedzi znajdzie Czytelnik w „Zombie atakują!”. To książka po prostu dla każdego. Menadżera korporacji, pracownika firmy, szpitala, urzędu, fundacji. Dla naukowca i studenta.  W prosty, zrozumiały i często zabawny sposób wyjaśnia problemy zarządzania ryzykiem, regulacji, zarządzania kryzysowego i zarządzania w ogóle, o których mówi się na całym świecie.<br/></span>
        <span>Lektura obowiązkowa dla wszystkich, którzy szukają sposobów na ryzyko, wszechobecne w biznesie i życiu prywatnym.</span>
        <span> </span>
        <span>To nie książka do poduszki, bo nie da ci zasnąć zanim jej całej nie przeczytasz! </span>
        <span> </span>
        <span> </span>
      </p>
    </description>
    <descriptionShort>Zarządzanie ryzykiem opisane w zrozumiały i często zabawny sposób. Lektura dla menadżera, pracownika firmy, urzędu, studenta i każdego, kto szuka sposobów na ryzyko w biznesie i w życiu prywatnym.</descriptionShort>
    <rating>0</rating>
  </product>
  <product>
    <title>Zombie atakują ! Zarządzanie ryzykiem po prostu.</title>
    <format>MOBI</format>
    <security>WM</security>
    <price>23.00</price>
    <isbn>978-83-272-3927-3</isbn>
    <coverId>144774</coverId>
    <authors>Dr Jerzy Podlewski</authors>
    <url>http://virtualo.pl/zombie_atakuja_zarzadzanie_ryzykiem_po_prostu/i128997/</url>
    <description>
      <p>Jaki apetyt na ryzyko miał Czerwony Kapturek ? Dlaczego firmy bankrutują, a ich menadżerowie nie piszą o tym książek?  Czy równouprawnienie zwiększa ryzyko w biznesie ?  Jak profesjonalnie przygotować się na nadejście Żywych Trupów ?</p>
      <p>
        <span>To niektóre, z wielu zaskakujących pytań, na które równie nieoczekiwane odpowiedzi znajdzie Czytelnik w „Zombie atakują!”. To książka po prostu dla każdego. Menadżera korporacji, pracownika firmy, szpitala, urzędu, fundacji. Dla naukowca i studenta.  W prosty, zrozumiały i często zabawny sposób wyjaśnia problemy zarządzania ryzykiem, regulacji, zarządzania kryzysowego i zarządzania w ogóle, o których mówi się na całym świecie.<br/></span>
        <span>Lektura obowiązkowa dla wszystkich, którzy szukają sposobów na ryzyko, wszechobecne w biznesie i życiu prywatnym.</span>
        <span> </span>
        <span>To nie książka do poduszki, bo nie da ci zasnąć zanim jej całej nie przeczytasz! </span>
        <span> </span>
        <span> </span>
      </p>
    </description>
    <descriptionShort>Zarządzanie ryzykiem opisane w zrozumiały i często zabawny sposób. Lektura dla menadżera, pracownika firmy, urzędu, studenta i każdego, kto szuka sposobów na ryzyko w biznesie i w życiu prywatnym.</descriptionShort>
    <rating>0</rating>
  </product>
  <product>
    <title>Konstytucja RP</title>
    <format>EPUB</format>
    <security>ADE</security>
    <price>32.30</price>
    <isbn>978-83-255-5174-2</isbn>
    <coverId>144953</coverId>
    <authors>Lech Garlicki</authors>
    <url>http://virtualo.pl/konstytucja_rp/i128998/</url>
    <description>
      <div>Autorem wprowadzenia niniejszej publikacji jest wybitny polski konstytucjonalista – prof. dr hab. Lech Garlicki z Uniwersytetu Warszawskiego. W latach 1993–2001 – sędzia Trybunału Konstytucyjnego, a obecnie – sędzia Europejskiego Trybunału</div>
      <div>Praw Człowieka w Strasburgu.</div>
      <div>Publikacja zawiera m.in.:</div>
      <div>– Konstytucję Rzeczypospolitej Polskiej,</div>
      <div>– Kodeks wyborczy,</div>
      <div>– ustawę o wykonywaniu mandatu posła i senatora,</div>
      <div>– ustawę o sejmowej komisji śledczej,</div>
      <div>– ustawę o Trybunale Konstytucyjnym,</div>
      <div>– ustawę o Trybunale Stanu,</div>
      <div>– ustawę o Rzeczniku Praw Obywatelskich,</div>
      <div>– ustawę o godle, barwach i hymnie Rzeczypospolitej Polskiej</div>
      <div>oraz o pieczęciach państwowych.</div>
    </description>
    <descriptionShort>Autorem wprowadzenia niniejszej publikacji jest wybitny polski konstytucjonalista – prof. dr hab. Lech Garlicki z Uniwersytetu Warszawskiego. W latach 1993–2001 – sędzia Trybunału Konstytucyjnego, a obecnie – sędzia ETPCz w Strasburgu.</descriptionShort>
    <rating>0</rating>
  </product>
  <product>
    <title>Drogowskazy</title>
    <format>EPUB</format>
    <security>WM</security>
    <price>26.60</price>
    <isbn>978-83-244-0313-4</isbn>
    <coverId>145056</coverId>
    <authors>Wiktor Osiatyński</authors>
    <url>http://virtualo.pl/drogowskazy/i128999/</url>
    <description>
      <p>Drogowskazy to podsumowanie przemyśleń i doświadczeń autora oraz  innych pisarzy i animatorów ruchu Anonimowych Alkoholików dotyczących  radzenia sobie z alkoholizmem i innymi uzależnieniami. Książka wytycza  drogę od analizy przyczyn, poprzez opis różnych form i stadiów  uzależnień, aż do zapisu działań, które musi podjąć każdy człowiek  chcący nie tylko decydować o sobie, ale także nadać swemu życiu sens.</p>
      <p> </p>
      <p> </p>
      <p><em>W kwietniu 1983 roku musiałem przestać pić. Niedługo później  trafiłem na pierwszy mityng Anonimowych Alkoholików. Po pół roku  abstynencji pojechałem na czterotygodniową kurację odwykową. Tam  pozbyłem się wszelkich złudzeń. Przekonałem się, że jestem alkoholikiem i  że muszę zrezygnować z alkoholu pod każdą postacią. Dowiedziałem się,  że alkoholizm wiązał się z niedojrzałością emocjonalną i brakiem  podstawowych umiejętności życiowych, choćby takich jak rozpoznawanie i  wyrażanie własnych uczuć, bezpieczne radzenie sobie z lękiem, złością i  samotnością, nawiązywanie i utrzymywanie nieegoistycznych relacji z  innymi ludźmi oraz wyznaczanie granic i umiejętność powiedzenia „nie”. I  że bez tych zdolności trudno będzie mi zachować trzeźwość.</em><br/>(ze wstępu)</p>
    </description>
    <descriptionShort>Drogowskazy to podsumowanie przemyśleń i doświadczeń autora oraz innych pisarzy i animatorów ruchu Anonimowych Alkoholików dotyczących radzenia sobie z alkoholizmem i innymi uzależnieniami.</descriptionShort>
    <rating>0</rating>
  </product>
  <product>
    <title>Powrót bogini. Część 1</title>
    <format>EPUB</format>
    <security>WM</security>
    <price>27.50</price>
    <isbn>978-83-238-9489-6</isbn>
    <coverId>145075</coverId>
    <authors>P.C Cast</authors>
    <url>http://virtualo.pl/powrot_bogini_czesc_1/i129000/</url>
    <description>
      <p>Shannon prowadzi szczęśliwe życie w mitycznym Partholonie. Wojna z Fomorianami skończyła się zwycięstwem, jej mąż, szaman Clan Fintan, wrócił do domu. Poddani kochają ją i czczą jako wybrankę bogini Epony. <span> </span>Nic nie zapowiada nadciągającego niebezpieczeństwa…</p>
      <p>Pewnego dnia Shannon traci przytomność. Budzi się w realnym świecie, z którego tak łatwo zrezygnowała i od którego odwykła. Powrót do rzeczywistości okazuje się bardzo bolesny. Za Shannon trafiły tu też siły zła, gotowe zniszczyć wszystko, co jest jej drogie</p>
      <p> </p>
    </description>
    <descriptionShort>Shannon prowadzi szczęśliwe życie w mitycznym Partholonie. Wojna z Fomorianami skończyła się zwycięstwem, jej mąż, szaman Clan Fintan, wrócił do domu</descriptionShort>
    <rating>0</rating>
  </product>
  <product>
    <title>Powrót bogini. Część 1</title>
    <format>MOBI</format>
    <security>WM</security>
    <price>27.50</price>
    <isbn>978-83-238-9489-6</isbn>
    <coverId>145078</coverId>
    <authors>P.C Cast</authors>
    <url>http://virtualo.pl/powrot_bogini_czesc_1/i129001/</url>
    <description>
      <p>Shannon prowadzi szczęśliwe życie w mitycznym Partholonie. Wojna z Fomorianami skończyła się zwycięstwem, jej mąż, szaman Clan Fintan, wrócił do domu. Poddani kochają ją i czczą jako wybrankę bogini Epony. <span> </span>Nic nie zapowiada nadciągającego niebezpieczeństwa…</p>
      <p>Pewnego dnia Shannon traci przytomność. Budzi się w realnym świecie, z którego tak łatwo zrezygnowała i od którego odwykła. Powrót do rzeczywistości okazuje się bardzo bolesny. Za Shannon trafiły tu też siły zła, gotowe zniszczyć wszystko, co jest jej drogie</p>
      <p> </p>
    </description>
    <descriptionShort>Shannon prowadzi szczęśliwe życie w mitycznym Partholonie. Wojna z Fomorianami skończyła się zwycięstwem, jej mąż, szaman Clan Fintan, wrócił do domu</descriptionShort>
    <rating>0</rating>
  </product>
  <product>
    <title>Powrót bogini. Część 2</title>
    <format>EPUB</format>
    <security>WM</security>
    <price>27.50</price>
    <isbn>978-83-238-9490-2</isbn>
    <coverId>145079</coverId>
    <authors>P.C Cast</authors>
    <url>http://virtualo.pl/powrot_bogini_czesc_2/i129002/</url>
    <description>
      <p> </p>
      <p> </p>
      <p>Shannon z trudem odnajduje się w realnym świecie. Jest przerażona odkryciem, że tu jej miejsce zajęła Rhiannon, prawdziwe wcielenie bogini Epony. Okrutna Rhiannon z rozmysłem krzywdzi bliskich Shannon. Jest potężna, bo przyzywa na pomoc siły ciemności. Nie odczuwa wyrzutów sumienia, a czynienie zła sprawia jej przyjemność.</p>
      <p> </p>
      <p>Shannon marzy o powrocie do mitycznego Partholonu, do kochanego męża i ludzi, którzy jej zaufali. Jednak najpierw musi stanąć do walki z Rhiannon i jej sojusznikami, by uratować ten świat przed zagładą…</p>
    </description>
    <descriptionShort>Shannon z trudem odnajduje się w realnym świecie. Jest przerażona odkryciem, że tu jej miejsce zajęła Rhiannon, prawdziwe wcielenie bogini Epony. Okrutna Rhiannon z rozmysłem krzywdzi bliskich Shannon.</descriptionShort>
    <rating>0</rating>
  </product>
  <product>
    <title>Powrót bogini. Część 2</title>
    <format>MOBI</format>
    <security>WM</security>
    <price>27.50</price>
    <isbn>978-83-238-9490-2</isbn>
    <coverId>145085</coverId>
    <authors>P.C Cast</authors>
    <url>http://virtualo.pl/powrot_bogini_czesc_2/i129003/</url>
    <description>
      <p>Shannon z trudem odnajduje się w realnym świecie. Jest przerażona odkryciem, że tu jej miejsce zajęła Rhiannon, prawdziwe wcielenie bogini Epony. Okrutna Rhiannon z rozmysłem krzywdzi bliskich Shannon. Jest potężna, bo przyzywa na pomoc siły ciemności. Nie odczuwa wyrzutów sumienia, a czynienie zła sprawia jej przyjemność.</p>
      <p> </p>
      <p>Shannon marzy o powrocie do mitycznego Partholonu, do kochanego męża i ludzi, którzy jej zaufali. Jednak najpierw musi stanąć do walki z Rhiannon i jej sojusznikami, by uratować ten świat przed zagładą…</p>
    </description>
    <descriptionShort>Shannon z trudem odnajduje się w realnym świecie. Jest przerażona odkryciem, że tu jej miejsce zajęła Rhiannon, prawdziwe wcielenie bogini Epony. Okrutna Rhiannon z rozmysłem krzywdzi bliskich Shannon.</descriptionShort>
    <rating>0</rating>
  </product>
  <product>
    <title>Matecznik</title>
    <format>MOBI</format>
    <security>WM</security>
    <price>19.30</price>
    <isbn>978-83-7033-871-8</isbn>
    <coverId>145261</coverId>
    <authors>Agnieszka Grzelak</authors>
    <url>http://virtualo.pl/matecznik/i129004/</url>
    <description>
      <p> </p>
      <p>Tu nie ma miejsca na nudę, warto spojrzeć na swoje życie z dystansem i przekonać się jaką może stworzyć niesamowitą fabułę, <em>Matecznik </em>daje taką możliwość!</p>
      <p>Dziennik zapracowanej kobiety, żony i matki czterech córek, nie musi być horrorem czy kryminałem... <em>Matecznik</em> to dziennik bohaterki Kamili, w której losach można się rozsmakować, jak we własnej codzienności. Autorka puszcza do nas oko, żebyśmy mogli z boku spojrzeć na swoje życie, w którym obok dni pełnych uśmiechu są też te gorsze, smutniejsze. Podkreśla, że jeteśmy ogromnie podobni do siebie w tej  "walce codziennej", od świąt do świąt, od wiosny do wiosny, w pragnieniu  zatrzymania czasu, żeby wczorajszą złość zamienić na uśmiech!</p>
      <p><strong><br/></strong><em>Temat jest mi tak bliski, że prawie nie widzę tekstu – jakby mi ktoś do głowy wlazł!</em><br/>Kasia, mama Macka, Hani i Janka</p>
      <p><em>Warto przeczytać, żeby poszpiegowac, co czuje kobieta – przyda się na co dzień.</em><br/>Karol, mąż z trzydziestoletnim stażem</p>
    </description>
    <descriptionShort>Dziennik zapracowanej kobiety, żony i matki czterech córek, nie musi być horrorem czy kryminałem...</descriptionShort>
    <rating>0</rating>
  </product>
  <product>
    <title>Jak czytać i rozumieć angielskie dokumenty sądowe w sprawach cywilnych?</title>
    <format>EPUB</format>
    <security>ADE</security>
    <price>75.05</price>
    <isbn>978-83-255-4910-7</isbn>
    <coverId>145292</coverId>
    <authors>Leszek Berezowski</authors>
    <url>http://virtualo.pl/jak_czytac_rozumiec_angielskie_dokumenty_sadowe_w/i129005/</url>
    <description>
      <p>Książka <strong><em>Jak czytać i rozumieć angielskie dokumenty sądowe w sprawach cywilnych?</em></strong> stanowi połączenie słownika, kursu angielskiego języka prawnego oraz wprowadzenia w zagadnienia i słownictwo  dokumentów sądowych  w sprawach cywilnych krajów anglosaskich.</p>
      <p>Jest to praktyczny przewodnik dla osób, które stykają się z dokumentami sądowymi w języku angielskim. W książce omówiono właściwości gramatyczne  tej odmiany języka, interpretacje całych zwrotów i zdań, wskazano również na zwyczaje, pojęcia, instytucje i tradycje właściwe dla krajów i  prawa angielskiego obszaru językowego. Poszczególne rozdziały przedstawiają dokumenty występujące w sprawach cywilnych toczących się przed sądami w krajach anglosaskich, poczynając od pozwu, a kończąc na wyroku sądu apelacyjnego. Niniejsza publikacja przeznaczona jest  dla prawników,  tłumaczy, a także dla menedżerów i studentów zainteresowanych opanowaniem umiejętności  czytania i prawidłowego rozumienia  tego typu tekstów w języku obcym.</p>
    </description>
    <descriptionShort>Książka Jak czytać i rozumieć angielskie dokumenty sądowe w sprawach cywilnych? stanowi połączenie słownika, kursu angielskiego języka prawnego oraz wprowadzenia w zagadnienia i słownictwo dokumentów sądowych w sprawach cywilnych ...</descriptionShort>
    <rating>0</rating>
  </product>
  <product>
    <title>Jak czytać i rozumieć angielskie umowy?</title>
    <format>EPUB</format>
    <security>ADE</security>
    <price>94.05</price>
    <isbn>978-83-255-4908-4</isbn>
    <coverId>145293</coverId>
    <authors>Leszek Berezowski</authors>
    <url>http://virtualo.pl/jak_czytac_rozumiec_angielskie_umowy/i129006/</url>
    <description>
      <p>Czwarte wydanie książki <em>Jak</em> <em>czytać i rozumieć angielskie umowy?</em> stanowi połączenie słownika, kursu angielskiego języka prawnego oraz wprowadze­nia w podstawowe zagadnienia prawa krajów anglosaskich. Jest to praktyczny przewodnik dla wszystkich osób, które stykają się z umo­wami pisanymi w języku angielskim.</p>
      <p>W książce szczegółowo omówiono terminologię występującą w umowach, właściwości gramatyczne angielskiego języka prawnego, przedstawiono interpretacje całych zwrotów i zdań na autentycznych przykładach oraz wskazano na anglosaskie zwyczaje, pojęcia, instytucje i tradycje kryjące się za doborem poszczególnych terminów. Czwarte wydanie książki zostało zaktualizowane i wzbogacone o podroz­dział dotyczący umowy spółki osobowej.</p>
    </description>
    <descriptionShort>Czwarte wydanie książki Jak czytać i rozumieć angielskie umowy? stanowi połączenie słownika, kursu angielskiego języka prawnego oraz wprowadze­nia w podstawowe zagadnienia prawa krajów anglosaskich.</descriptionShort>
    <rating>0</rating>
  </product>
  <product>
    <title>Szympansy z azylu Fauna. O przetrwaniu i woli życia</title>
    <format>EPUB</format>
    <security>WM</security>
    <price>29.30</price>
    <isbn>978-83-7536-635-8</isbn>
    <coverId>145389</coverId>
    <authors>Andrew Westoll</authors>
    <url>http://virtualo.pl/szympansy_azylu_fauna_przetrwaniu_woli_zycia/i129007/</url>
    <description>
      <p>Z niekompletnej dokumentacji medycznej wynika, że Tom przez ponad  trzydzieści lat przeszedł co najmniej sześćdziesiąt trzy biopsje  wątroby, szpiku i węzłów chłonnych, został zarażony wirusem HIV i  wirusem zapalenia wątroby, a przytomności pozbawiono go trzysta  sześćdziesiąt dziewięć razy.</p>
      <p>Niewiele lepiej wyglądają karty medyczne Regisa, cukrzyka, który nie  chce przyjmować insuliny, Sue Ellen, której w młodości młotkiem wybito  zęby, cierpiącej na klaustrofobię Pepper i Chance, która pierwsze pięć  lat życia spędziła w kompletnej izolacji. Łączy je to, że wszystkie mają  poważne zaburzenia psychiczne. I to, że wszystkie znalazły schronienie  na farmie Glorii Grow.</p>
      <p>Zaczęło się pod koniec lat dziewięćdziesiątych, kiedy przed siedzibą  fundacji Fauna zaparkował czarny pick-up holujący zwykłą przyczepę dla  koni. W środku znajdowało się kilka szympansów, dla których był to kres  długiej i trudnej podróży. Aż do tego dnia stanowiły własność  Uniwersytetu Nowojorskiego, gdzie były obiektami eksperymentów  biomedycznych. Wydarte matkom tuż po urodzeniu, trzymane w ciasnych  klatkach, poddawane inwazyjnym operacjom, badaniom neurologicznym  i toksykologicznym nigdy nie odzyskają pełnej sprawności, ale w azylu  Fauna w spokoju dochodzą do siebie.</p>
      <p>Dla Andrew Westolla wolontariat w azylu miał być wielką przygodą,  spotkaniem oko w oko z najbliższym kuzynem człowieka. Ale wyobrażał  ją sobie zupełnie inaczej.</p>
      <p> </p>
      <p>Polecamy także film <em><a>Dzikie z natury</a></em></p>
    </description>
    <descriptionShort>Dla Andrew Westolla wolontariat w azylu miał być wielką przygodą, spotkaniem oko w oko z najbliższym kuzynem człowieka. Ale wyobrażał ją sobie zupełnie inaczej.</descriptionShort>
    <rating>0</rating>
  </product>
  <product>
    <title>Futbol jest okrutny</title>
    <format>EPUB</format>
    <security>WM</security>
    <price>25.60</price>
    <isbn>978-83-7536-634-1</isbn>
    <coverId>145390</coverId>
    <authors>Michał Okoński</authors>
    <url>http://virtualo.pl/futbol_jest_okrutny/i129008/</url>
    <description>
      <div>
        <p>„Wiecie, jak to jest żyć z perspektywą  wykitowania podczas meczu, w dodatku perspektywą naukowo potwierdzoną?  Dlaczego ministerstwo zdrowia, a niechby nawet ministerstwo sportu nie  informuje, że oglądanie Tottenhamu może być przyczyną wielu groźnych  chorób?” – to brzmi jak fragment <em>Futbolowej gorączki</em> Nicka Hornby’ego, choć dotyczy klubu, z którym Hornby jako kibic Arsenalu raczej nie chciałby mieć nic wspólnego. <em>Futbol jest okrutn</em>y  to pełna humoru autoanaliza kibicowskiego uzależnienia: opowieść o tym,  jak piłka nożna niepostrzeżenie zagarnia kolejne przestrzenie życia  dziennikarza „Tygodnika Powszechnego”, jak komplikuje udział w  arcyważnej naradzie kierownictwa firmy, jak wpływa na wychowywanie  dzieci i relacje z własnym ojcem, jak zmienia myślenie o seksie i  śmierci.</p>
        <p>Równocześnie jest to opowieść o chorobach i wielkości współczesnej  piłki. Z jednej strony komercja, bankrutujące kluby, rasizm, seksizm  i homofobia, ciężki los sędziów i zmarnowane życie dawnych gwiazd,  z drugiej futbol jako narzędzie społecznej zmiany – kluby odbudowywane  przez kibiców, piłkarze zaangażowani w pomaganie innym, sto osiem podań  Barcelony i piętnaście minut w szatni Liverpoolu. Jednym słowem: futbol  w jego absolutnej narracyjnej nieprzewidywalności, z nieustającym Fergie  Time, czyli meczami rozstrzyganymi w ostatnich sekundach ostatniej  kolejki ostatniego sezonu. Rozważna i romantyczna opowieść o „pięknej  grze”, której patronami są inni kibice inteligenci: Marek Bieńczyk,  Jerzy Pilch, Ken Loach i... Jan Paweł II.</p>
      </div>
    </description>
    <descriptionShort>Futbol jest okrutny to pełna humoru autoanaliza kibicowskiego uzależnienia: opowieść o tym, jak piłka nożna niepostrzeżenie zagarnia kolejne przestrzenie życia dziennikarza.</descriptionShort>
    <rating>0</rating>
  </product>
  <product>
    <title>Zamieć</title>
    <format>EPUB</format>
    <security>WM</security>
    <price>25.60</price>
    <isbn>978-83-7536-633-4</isbn>
    <coverId>145392</coverId>
    <authors>Władimir Sorokin</authors>
    <url>http://virtualo.pl/zamiec/i129009/</url>
    <description>
      <p>Podczas zimowej zamieci doktor Płaton Iljicz Garin pośpiesznie  usiłuje dotrzeć ze szczepionką do wsi ogarniętej epidemią tajemniczego  boliwijskiego wirusa. Wyprasza konie na stacji i z chlebowozem Chrząkałą  rusza na oślep w śnieg. W nieprzeniknionym lodowatym świecie,  w białych, niemal narkotycznych przestrzeniach czyha jednak na niego  świat rosyjskiego folkloru — odżywają olbrzymy i karły, z zasp wyrastają  kryształowe piramidy. Nie wie, czy dojedzie do celu. Nie domyśla się,  kto czeka na niego u kresu podróży. W fantasmagorycznej powieści  Władimira Sorokina futurystyczna wyobraźnia łączy się z czechowowską  narracją, tworząc niezwykłą postmodernistyczną mieszankę.</p>
      <p>Książka jest laureatką Krajowej Nagrody Literackiej „Nowaja  słowiesnost” (”NOS”) 2011 i Nagrody Literackiej „Bolszaja kniga” 2011  (2. miejsce).</p>
    </description>
    <descriptionShort>W fantasmagorycznej powieści Władimira Sorokina futurystyczna wyobraźnia łączy się z czechowowską narracją, tworząc niezwykłą postmodernistyczną mieszankę.</descriptionShort>
    <rating>0</rating>
  </product>
  <product>
    <title>AlterPOP - numer 3 - maj-czerwiec 2012</title>
    <format>PDF</format>
    <security/>
    <price>1.10</price>
    <isbn/>
    <coverId>145400</coverId>
    <authors>Opracowanie zbiorowe</authors>
    <url>http://virtualo.pl/alterpop_numer_-_maj-czerwiec_2012/i129010/</url>
    <description>
      <p>Trzeci numer magazynu popkulturalnego Alterpop zawiera <strong>96 stron</strong>, na których można znaleźć:</p>
      <p>– przeglądy premier płytowych, filmowych, książkowych oraz gier, <br/>– wywiady: <strong>Mariusz Duda</strong>, <strong>Grzegorz Rogala</strong>, <strong>Beth Hart</strong>, <br/>– ekskluzywne recenzje płyt, filmów, seriali, książek i gier, <br/>– dla fanów <strong>Jonathana Carrola</strong>: pełen tekst jednego z najnowszych opowiadań oraz konkurs z 2 egzemplarzami zbioru<em>Kobieta, która wyszła za chmurę</em>, <br/>– dla fanów <strong>Woody’ego Allena</strong>: obszerny fragment najnowszej książki-wywiadu.</p>
      <p>Ponadto refleksja na temat stanu <strong>Internetu</strong> – dystrybucja on-line, ACTA, Facebook oraz możliwości sieci mobilnej</p>
    </description>
    <descriptionShort>AlterPOP - popkultura alternatywna</descriptionShort>
    <rating>0</rating>
  </product>
  <product>
    <title>Alterpop - numer 4 - lipiec-sierpień 2012</title>
    <format>PDF</format>
    <security/>
    <price>1.10</price>
    <isbn/>
    <coverId>145401</coverId>
    <authors>Opracowanie zbiorowe</authors>
    <url>http://virtualo.pl/alterpop_numer_-_lipiec-sierpien_2012/i129011/</url>
    <description>
      <p>Czwarty numer magazynu popkulturalnego Alterpop zawiera <strong>74 strony</strong>, na których można znaleźć:</p>
      <p>– <strong>przeglądy premier</strong> płytowych, filmowych, książkowych oraz gier <br/>– <strong>ekskluzywne recenzje</strong> płyt, filmów, książek i gier, <br/>– wywiad z operatorem filmowym <strong>Jackiem Petryckim</strong>, <br/>– najnowsze opowiadanie <strong>Dawida Brykalskiego</strong>, <br/>– a dla fanów <strong>Slasha</strong>: fragment jego autobiografii.</p>
      <p>Ponadto dalsza część rozważań na temat <strong>Internetu i praw autorskich</strong>.</p>
    </description>
    <descriptionShort>Alterpop - popkultura alternatywna</descriptionShort>
    <rating>0</rating>
  </product>
  <product>
    <title>Alterpop - numer 5 - wrzesień-październik 2012</title>
    <format>PDF</format>
    <security/>
    <price>1.10</price>
    <isbn/>
    <coverId>145402</coverId>
    <authors>Opracowanie zbiorowe</authors>
    <url>http://virtualo.pl/alterpop_numer_-_wrzesien-pazdziernik_2012/i129012/</url>
    <description>
      <p>Piąty numer magazynu popkulturalnego Alterpop zawiera <strong>70 stron</strong>, na których można znaleźć:</p>
      <p>– <strong>przeglądy premier</strong> płytowych, filmowych, książkowych oraz gier <br/>– wywiady z pisarzem <strong>Andrzejem Pilipiukiem</strong> i muzykiem <strong>Ryszardem Wolbachem</strong> (temat z okładki), <br/>– <strong>ekskluzywne recenzje</strong> płyt, filmów, książek i gier, <br/>– a dla fanów <strong>Johnny'ego Deppa</strong>: fragment jego nowej biografii.</p>
      <p>Ponadto poruszamy kwestię <strong>squatingu</strong> w Polsce.</p>
    </description>
    <descriptionShort>Alterpop - popkultura alternatywna</descriptionShort>
    <rating>0</rating>
  </product>
  <product>
    <title>Alterpop - numer 6 - listopad 2012</title>
    <format>PDF</format>
    <security/>
    <price>1.10</price>
    <isbn/>
    <coverId>145403</coverId>
    <authors>Opracowanie zbiorowe</authors>
    <url>http://virtualo.pl/alterpop_numer_-_listopad_2012/i129013/</url>
    <description>
      <p>Szósty numer magazynu popkulturalnego Alterpop zawiera <strong>46 stron</strong>, na których można znaleźć:</p>
      <p>– <strong>przeglądy premier</strong> płytowych, filmowych oraz gier <br/>– ekskluzywne fragmenty biografii frontmana <strong>AC/DC</strong> - Briana Johnsona, <br/>– <strong>recenzje</strong> płyt, filmów i gier, <br/>– a dla fanów <strong>The Rolling Stones</strong>: historia najbardziej rozpoznawalnego logo show-biznesu.</p>
      <p>Ponadto dobieramy podkład muzyczny dla wyczynu <strong>Felixa Baumgartnera</strong> i zapowiadamy <strong>Festiwal Ambientalny</strong>.</p>
    </description>
    <descriptionShort>Alterpop - popkultura alternatywna</descriptionShort>
    <rating>0</rating>
  </product>
  <product>
    <title>Alterpop - numer 7 - grudzień 2012</title>
    <format>PDF</format>
    <security/>
    <price>1.10</price>
    <isbn/>
    <coverId>145404</coverId>
    <authors>Opracowanie zbiorowe</authors>
    <url>http://virtualo.pl/alterpop_numer_-_grudzien_2012/i129014/</url>
    <description>
      <p> </p>
      <p>Siódmy numer magazynu popkulturalnego Alterpop zawiera <strong>70 stron</strong>, na których można znaleźć:</p>
      <p>– <strong>przeglądy premier</strong> płytowych, filmowych oraz gier, <br/>– wywiady z zespołami <strong>Hipgnosis</strong>, <strong>Rebeka</strong><br/>oraz z producentem filmowym <strong>Arkadiuszem Wojnarowskim</strong>, <br/>– <strong>recenzje</strong> płyt, filmów, książek i gier, <br/>– fragment najnowszej książki o <strong>Pink Floyd</strong>.</p>
      <p>Ponadto przyglądamy się wszystkim twarzom <strong>Jokera</strong>, analizujemy współpracę <strong>Asi i Kotów</strong> z wytwórnią <strong>Nasiono Records</strong> i zapowiadamy <strong>Wee Dub Festival</strong>.</p>
    </description>
    <descriptionShort>Alterpop - popkultura alternatywna</descriptionShort>
    <rating>0</rating>
  </product>
  <product>
    <title>Alterpop - numer 8 - styczeń 2013</title>
    <format>PDF</format>
    <security/>
    <price>1.10</price>
    <isbn/>
    <coverId>145405</coverId>
    <authors>Opracowanie zbiorowe</authors>
    <url>http://virtualo.pl/alterpop_numer_-_styczen_2013/i129015/</url>
    <description>
      <p> </p>
      <p>Ósmy numer magazynu popkulturalnego Alterpop zawiera <strong>44 strony</strong>, na których można znaleźć:</p>
      <p>– <strong>przeglądy premier</strong> płytowych, filmowych oraz gier, <br/>– zapowiedzi najlepszych gier roku <strong>2013</strong>, <br/>– <strong>recenzje</strong> filmów i książek,</p>
      <p>Ponadto przypominamy postać <strong>Żbika</strong> i PRL-owskie komiksy o nim, a tematem z okładki jest <strong>Joe Strummer</strong>.</p>
    </description>
    <descriptionShort>Alterpop - popkultura alternatywna</descriptionShort>
    <rating>0</rating>
  </product>
  <product>
    <title>Alterpop - numer 9 - luty-marzec 2013</title>
    <format>PDF</format>
    <security/>
    <price>1.10</price>
    <isbn/>
    <coverId>145406</coverId>
    <authors>Opracowanie zbiorowe</authors>
    <url>http://virtualo.pl/alterpop_numer_-_luty-marzec_2013/i129016/</url>
    <description>
      <p> </p>
      <p>Dziewiąty numer magazynu popkulturalnego Alterpop zawiera <strong>50 strony</strong>, na których:</p>
      <p>– <strong>przeglądy premier</strong> płytowych, filmowych, książkowych i gier, <br/>– <strong>komiks</strong> w <strong>kinie</strong>, czyli co się stało z popkulturą, <br/>– książki <strong>Chucka Palahniuka</strong> <br/>– twórczość zespołu <strong>Swans</strong>, <br/>– ekskluzywne <strong>recenzje</strong> książek i gier,</p>
      <p>Ponadto fragment kowbojskiej komedii pt. <strong>Bracia Sisters</strong> i katastroficzna wizja Gdańska w komiksie <strong>Doktor Damiano</strong>.</p>
    </description>
    <descriptionShort>Alterpop - popkultura alternatywna</descriptionShort>
    <rating>0</rating>
  </product>
  <product>
    <title>Alterpop - numer 10 - kwiecień 2013</title>
    <format>PDF</format>
    <security/>
    <price>1.10</price>
    <isbn/>
    <coverId>145407</coverId>
    <authors>Opracowanie zbiorowe</authors>
    <url>http://virtualo.pl/alterpop_numer_10_kwiecien_2013/i129017/</url>
    <description>
      <p>
        <span>Jubileuszowy numer magazynu popkulturalnego Alterpop zawiera </span>
        <strong>64 strony</strong>
        <span>, na których:</span>
      </p>
      <p> </p>
      <p>– <strong>przeglądy premier</strong> płytowych, filmowych i książkowych, <br/>– <strong>David Bowie</strong> – portret antykameleona, <br/>– rozmowa z Tomaszem Sikorą z grupy <strong>Karbido</strong>, <br/>– propozycje <strong>komiksowe</strong>,</p>
      <p>Ponadto zapowiadamy animowanego <strong>Kapuścińskiego</strong> i publikujemy opowiadanie ze zbioru <strong>Czereśnie prosto z drzewa </strong>Karola Ketzera.</p>
    </description>
    <descriptionShort>Alterpop - popkultura alternatywna</descriptionShort>
    <rating>0</rating>
  </product>
  <product>
    <title>Szeregowiec</title>
    <format>EPUB</format>
    <security>WM</security>
    <price>11.00</price>
    <isbn>978-83-7859-159-7</isbn>
    <coverId>145409</coverId>
    <authors>Adrian K. Antosik</authors>
    <url>http://virtualo.pl/szeregowiec/i129018/</url>
    <description>
      <p>Dawid został złapany i zastrzelony przez terrorystów w współczesnym świecie. Smutny koniec młodzieńczego życia…<br/>… i zarazem początek czegoś nowego. Obudził się w dalekiej przyszłości, w której prawie już nie ma ludzi. Został sprowadzony z przeszłości w ramach projektu mającego na celu odrodzenie ludzkości.<br/>W czasach gdzie ostatni potomkowie ludzi zwani Odwiecznymi rozpierzchli się po wszechświecie terraformując planety i systemy oraz zamieszkując je. Nieliczni pozostali w układzie słonecznym Ziemi odnaleźli sposób by "bezkarnie" sprowadzać ludzi z przeszłości. Jednak czy ludzie „z przeszłości” dadzą sobie radę w nowej rzeczywistości?</p>
    </description>
    <descriptionShort>Dawid został złapany i zastrzelony przez terrorystów w współczesnym świecie. Smutny koniec młodzieńczego życia…</descriptionShort>
    <rating>0</rating>
  </product>
  <product>
    <title>Piórem przez epoki</title>
    <format>EPUB</format>
    <security>WM</security>
    <price>9.20</price>
    <isbn>978-83-7859-148-1</isbn>
    <coverId>145418</coverId>
    <authors>Maria Teresa Pietrzak</authors>
    <url>http://virtualo.pl/piorem_przez_epoki/i129019/</url>
    <description>
      <p>Wielokrotnie pragnęłam napisać wspaniałą powieść traktującą, bądź to o czasach w których aktualnie żyłam, bądź o czasach minionych. Jednak podejmowane przeze mnie próby zazwyczaj kończyły się niepowodzeniem.<br/><br/>Ponieważ jestem niecierpliwa i wszystko co robię chcę skończyć jak najprędzej, by móc, od razu zacząć coś nowego wielkie plany zamieniały się w małe planiki, a z powieści najczęściej wychodziły opowiadania, które, niejednokrotnie mnie samą zaskakiwały swoim zakończeniem. A jeśli czegoś nie potrafiłam wyrazić prozą, wówczas sięgałam po rymy.<br/><br/>I w ten sposób, na przestrzeni dwudziestu z górą lat zebrał się mały zbiorek nieco satyrycznych opowiadań i wierszy pod wspólnym tytułem „Piórem przez epoki”</p>
    </description>
    <descriptionShort>mały zbiorek nieco satyrycznych opowiadań i wierszy pod wspólnym tytułem „Piórem przez epoki”</descriptionShort>
    <rating>0</rating>
  </product>
  <product>
    <title>Futbol jest okrutny</title>
    <format>MOBI</format>
    <security>WM</security>
    <price>25.60</price>
    <isbn>978-83-7536-634-1</isbn>
    <coverId>145424</coverId>
    <authors>Michał Okoński</authors>
    <url>http://virtualo.pl/futbol_jest_okrutny/i129020/</url>
    <description>
      <div>
        <p>„Wiecie, jak to jest żyć z perspektywą  wykitowania podczas meczu, w dodatku perspektywą naukowo potwierdzoną?  Dlaczego ministerstwo zdrowia, a niechby nawet ministerstwo sportu nie  informuje, że oglądanie Tottenhamu może być przyczyną wielu groźnych  chorób?” – to brzmi jak fragment <em>Futbolowej gorączki</em> Nicka Hornby’ego, choć dotyczy klubu, z którym Hornby jako kibic Arsenalu raczej nie chciałby mieć nic wspólnego. <em>Futbol jest okrutn</em>y  to pełna humoru autoanaliza kibicowskiego uzależnienia: opowieść o tym,  jak piłka nożna niepostrzeżenie zagarnia kolejne przestrzenie życia  dziennikarza „Tygodnika Powszechnego”, jak komplikuje udział w  arcyważnej naradzie kierownictwa firmy, jak wpływa na wychowywanie  dzieci i relacje z własnym ojcem, jak zmienia myślenie o seksie i  śmierci.</p>
        <p>Równocześnie jest to opowieść o chorobach i wielkości współczesnej  piłki. Z jednej strony komercja, bankrutujące kluby, rasizm, seksizm  i homofobia, ciężki los sędziów i zmarnowane życie dawnych gwiazd,  z drugiej futbol jako narzędzie społecznej zmiany – kluby odbudowywane  przez kibiców, piłkarze zaangażowani w pomaganie innym, sto osiem podań  Barcelony i piętnaście minut w szatni Liverpoolu. Jednym słowem: futbol  w jego absolutnej narracyjnej nieprzewidywalności, z nieustającym Fergie  Time, czyli meczami rozstrzyganymi w ostatnich sekundach ostatniej  kolejki ostatniego sezonu. Rozważna i romantyczna opowieść o „pięknej  grze”, której patronami są inni kibice inteligenci: Marek Bieńczyk,  Jerzy Pilch, Ken Loach i... Jan Paweł II.</p>
      </div>
    </description>
    <descriptionShort>Futbol jest okrutny to pełna humoru autoanaliza kibicowskiego uzależnienia: opowieść o tym, jak piłka nożna niepostrzeżenie zagarnia kolejne przestrzenie życia dziennikarza.</descriptionShort>
    <rating>0</rating>
  </product>
  <product>
    <title>Zamieć</title>
    <format>MOBI</format>
    <security>WM</security>
    <price>25.60</price>
    <isbn>978-83-7536-633-4</isbn>
    <coverId>145452</coverId>
    <authors>Władimir Sorokin</authors>
    <url>http://virtualo.pl/zamiec/i129021/</url>
    <description>
      <p>Podczas zimowej zamieci doktor Płaton Iljicz Garin pośpiesznie  usiłuje dotrzeć ze szczepionką do wsi ogarniętej epidemią tajemniczego  boliwijskiego wirusa. Wyprasza konie na stacji i z chlebowozem Chrząkałą  rusza na oślep w śnieg. W nieprzeniknionym lodowatym świecie,  w białych, niemal narkotycznych przestrzeniach czyha jednak na niego  świat rosyjskiego folkloru — odżywają olbrzymy i karły, z zasp wyrastają  kryształowe piramidy. Nie wie, czy dojedzie do celu. Nie domyśla się,  kto czeka na niego u kresu podróży. W fantasmagorycznej powieści  Władimira Sorokina futurystyczna wyobraźnia łączy się z czechowowską  narracją, tworząc niezwykłą postmodernistyczną mieszankę.</p>
      <p>Książka jest laureatką Krajowej Nagrody Literackiej „Nowaja  słowiesnost” (”NOS”) 2011 i Nagrody Literackiej „Bolszaja kniga” 2011  (2. miejsce).</p>
    </description>
    <descriptionShort>W fantasmagorycznej powieści Władimira Sorokina futurystyczna wyobraźnia łączy się z czechowowską narracją, tworząc niezwykłą postmodernistyczną mieszankę.</descriptionShort>
    <rating>0</rating>
  </product>
  <product>
    <title>Pani Walewska</title>
    <format>EPUB</format>
    <security>WM</security>
    <price>18.30</price>
    <isbn>978-83-7779-026-7</isbn>
    <coverId>145456</coverId>
    <authors>Marian Brandys</authors>
    <url>http://virtualo.pl/pani_walewska/i129022/</url>
    <description>
      <p>Jeden z najpiękniejszych romansów w historii i literaturze polskiej. Wszystko zaczęło się od niezwykłego spotkania, gdy młodziutka pani Walewska wyjechała pod Warszawę, by powitać wielkiego cesarza Francuzów, który miał przynieść wolność państwu polskiemu. Wychowana w jego kulcie, do końca życia nie straciła wiary w gwiazdę Napoleona. Do związku z nim pchała ją cała śmietanka towarzyska Warszawy, łącznie z patriotami, którzy wierzyli, że Napoleon zakochany więcej uczyni dla Polski, niż Napoleon – polityk. I rzeczywiście Napoleon zakochał się, żadnej jego pozamałżeński związek nie trwał tak długo jak ten z Marią. A on stał się dla niej miłością życia.</p>
    </description>
    <descriptionShort>Historia słynnego romansu Marii z Łączyńskich Walewskiej z Napoleonem. Ich związek trwał kilka lat, a jego owocem był syn Aleksander. Kiedy gwiazda Napoleona gasła, Maria jako jedyna z jego kobiet, odwiedziła cesarza na Elbie.</descriptionShort>
    <rating>0</rating>
  </product>
  <product>
    <title>Pani Walewska</title>
    <format>MOBI</format>
    <security>WM</security>
    <price>18.30</price>
    <isbn>978-83-7779-026-7</isbn>
    <coverId>145457</coverId>
    <authors>Marian Brandys</authors>
    <url>http://virtualo.pl/pani_walewska/i129023/</url>
    <description>
      <p>Jeden z najpiękniejszych romansów w historii i literaturze polskiej. Wszystko zaczęło się od niezwykłego spotkania, gdy młodziutka pani Walewska wyjechała pod Warszawę, by powitać wielkiego cesarza Francuzów, który miał przynieść wolność państwu polskiemu. Wychowana w jego kulcie, do końca życia nie straciła wiary w gwiazdę Napoleona. Do związku z nim pchała ją cała śmietanka towarzyska Warszawy, łącznie z patriotami, którzy wierzyli, że Napoleon zakochany więcej uczyni dla Polski, niż Napoleon – polityk. I rzeczywiście Napoleon zakochał się, żadnej jego pozamałżeński związek nie trwał tak długo jak ten z Marią. A on stał się dla niej miłością życia.</p>
    </description>
    <descriptionShort>Historia słynnego romansu Marii z Łączyńskich Walewskiej z Napoleonem. Ich związek trwał kilka lat, a jego owocem był syn Aleksander. Kiedy gwiazda Napoleona gasła, Maria jako jedyna z jego kobiet, odwiedziła cesarza na Elbie.</descriptionShort>
    <rating>0</rating>
  </product>
  <product>
    <title>Drogowskazy</title>
    <format>MOBI</format>
    <security>WM</security>
    <price>26.60</price>
    <isbn>978-83-244-0313-4</isbn>
    <coverId>145468</coverId>
    <authors>Wiktor Osiatyński</authors>
    <url>http://virtualo.pl/drogowskazy/i129024/</url>
    <description>
      <p>Drogowskazy to podsumowanie przemyśleń i doświadczeń autora oraz  innych pisarzy i animatorów ruchu Anonimowych Alkoholików dotyczących  radzenia sobie z alkoholizmem i innymi uzależnieniami. Książka wytycza  drogę od analizy przyczyn, poprzez opis różnych form i stadiów  uzależnień, aż do zapisu działań, które musi podjąć każdy człowiek  chcący nie tylko decydować o sobie, ale także nadać swemu życiu sens.</p>
      <p> </p>
      <p> </p>
      <p><em>W kwietniu 1983 roku musiałem przestać pić. Niedługo później  trafiłem na pierwszy mityng Anonimowych Alkoholików. Po pół roku  abstynencji pojechałem na czterotygodniową kurację odwykową. Tam  pozbyłem się wszelkich złudzeń. Przekonałem się, że jestem alkoholikiem i  że muszę zrezygnować z alkoholu pod każdą postacią. Dowiedziałem się,  że alkoholizm wiązał się z niedojrzałością emocjonalną i brakiem  podstawowych umiejętności życiowych, choćby takich jak rozpoznawanie i  wyrażanie własnych uczuć, bezpieczne radzenie sobie z lękiem, złością i  samotnością, nawiązywanie i utrzymywanie nieegoistycznych relacji z  innymi ludźmi oraz wyznaczanie granic i umiejętność powiedzenia „nie”. I  że bez tych zdolności trudno będzie mi zachować trzeźwość.</em><br/>(ze wstępu)</p>
    </description>
    <descriptionShort>Drogowskazy to podsumowanie przemyśleń i doświadczeń autora oraz innych pisarzy i animatorów ruchu Anonimowych Alkoholików dotyczących radzenia sobie z alkoholizmem i innymi uzależnieniami.</descriptionShort>
    <rating>0</rating>
  </product>
  <product>
    <title>Socjologia edukacji. Podręcznik akademicki</title>
    <format>EPUB</format>
    <security>WM</security>
    <price>23.00</price>
    <isbn>978-83-7850-404-7</isbn>
    <coverId>145480</coverId>
    <authors>prof. J. Mirosław Szymański</authors>
    <url>http://virtualo.pl/socjologia_edukacji_podrecznik_akademicki/i129025/</url>
    <description>
      <p>
        <span>
          <span> Wzrost znaczenia edukacji we współczesnym świecie powoduje coraz  większe zainteresowanie socjologów tą dziedziną życia społecznego.  Obecnie można już mówić o ukształtowaniu się socjologii edukacji jako  ważnej sudyscypliny socjologii. Przygotowany podręcznik umożliwia  zaznajomienie się z dominującą problematyką studiów i badań w zakresie  socjologii edukacji. Autor charakteryzuje socjologię edukacji jako  dziedzinę wiedzy. Omawia edukacyjne znaczenie takich procesów  społecznych, jak: stratyfikacja społeczna, zmiana społeczna,  socjalizacja, współczesne kształcenie i wychowanie. Przedstawia analizy  dotyczące jednostki i społeczeństwa. Charakteryzuje funkcje edukacyjne  instytucji: rodziny, szkoły, zakładu pracy, ośrodków władzy. Ukazuje  tworzące się w społeczeństwie współczesnym napięcia między  indywidualizmem a wspólnotowością, wartościami i antywartościami,  dążeniami do równości społecznej i narastającymi nierównościami,  reprodukcją społeczną a emancypacją jednostek i grup społecznych.  Końcowa część pracy dotyczy kształtowania tożsamości, procesu będącego  jednym z najważniejszych wyzwań socjalizacyjnych i wychowawczych naszych  czasów.</span>
        </span>
      </p>
      <p>
        <span>
          <span> Podręcznik zawiera obszerną bibliografię, słownik ważniejszych  terminów, problemy do przemyślenia i dyskusji. Może być wykorzystywany  przez studentów, a także przez inne osoby zainteresowane socjologicznymi  zagadnieniami współczesnej edukacji.</span>
        </span>
      </p>
      <p>
        <br/>
        <strong>
          <span>
            <span>Seria autorskich podręczników akademickich Pedagogika Nauce i Praktyce:<br/><br/></span>
          </span>
        </strong>
      </p>
      <p>
        <span>
          <span>1. Pedagogika ogólna. Podstawowe prawidłowości </span>
        </span>
        <span>
          <span>(<a>opis książki</a>)</span>
        </span>
      </p>
      <p>
        <span>
          <span>2. Dydaktyka. Podrecznik akademicki </span>
        </span>
        <span>
          <span>(<a>opis książki</a>)</span>
        </span>
      </p>
      <p>
        <span>
          <span>3. Z dziejów teorii i praktyki wychowania. Podrecznik akademicki  (<a>opis książki</a>)<br/></span>
        </span>
      </p>
      <p>
        <span>
          <span>4. Socjologia edukacji. </span>
        </span>
        <span>
          <span>Podrecznik akademicki </span>
        </span>
      </p>
      <p>
        <span>
          <span> Seria autorskich podręczników akade­mickich do pedagogiki jest  kolejnym  do­pełnieniem polskiej literatury przedmiotu o  nowe IMPULSY i   spojrzenie na przed­miot jej naukowych badań, najbardziej palące dla   praktyki problemy eduka­cyjne, opiekuńcze i wychowawcze oraz klasyczne   lub/i nieznane jeszcze sposoby podejścia do ich rozwiązywania. W pono-   woczesnej dobie naukowa wiedza rozwi­ja się z nieprawdopodobną dynamiką,   intensywnością i częstotliwością, toteż coraz trudniej jest adeptom  tej  profesji odnaleźć się w jej labiryncie. Autorzy serii wydawniczej   jednak zarówno potwier­dzają aktualność przekazywanej nam wiedzy, jak i   wychodzą w przyszłość z tym, co warte jest zatrzymania, reflek­sji czy   dalszych badań. Właśnie dlatego nadałem tej serii tytuł: PEDAGOGIKA   NAUCE I PRAKTYCE, bo każdy z auto­rów, pracując nad zakresem   tematycz­nym własnej subdyscypliny naukowej, łączy w akademickim i   podręczniko­wym zarazem przekazie teraźniejszość z przyszłością, która   na naszych oczach i tak staje się już przeszłością.</span>
        </span>
      </p>
      <p>
        <span>
          <span> Czytelnikom podręczników nie tylko ży­czę miłej lektury, ale i  zachęcam  do wspól­nej debaty, krytyki i recenzji, które nam wszystkim  pomogą w  doskonaleniu włas­nej twórczości.</span>
        </span>
      </p>
      <p>
        <span>
          <span>prof. dr hab. Bogusław Śliwerski</span>
        </span>
      </p>
    </description>
    <descriptionShort>Podręcznik jest bardzo dobrze przygotowany – pod każdym względem. Autor bez żadnych problemów porusza się po wchodzących w skład podręcznika zagadnieniach, a jego analizy są dobrze przygotowane.</descriptionShort>
    <rating>0</rating>
  </product>
  <product>
    <title>Polityka nr 17/18/2013</title>
    <format>PDF</format>
    <security/>
    <price>3.60</price>
    <isbn/>
    <coverId>145486</coverId>
    <authors>Opracowanie zbiorowe</authors>
    <url>http://virtualo.pl/polityka_nr_17_18_2013/i129026/</url>
    <description>
      <p>POLITYKA to najlepiej sprzedający się tygodnik na polskim rynku,  ukazujący się nieprzerwanie od 1957 roku. Tematyka obejmuje bieżące  wydarzenia polityczne, gospodarcze, naukowe i kulturalne z Polski,  Europy i ze świata. Każdy numer to raporty i pogłębione analizy, to  felietony i reportaże najznakomitszych polskich dziennikarzy i  komentatorów.</p>
    </description>
    <descriptionShort>Wydanie (2905) z dn. 24 kwietnia 2013 r.</descriptionShort>
    <rating>0</rating>
  </product>
  <product>
    <title>Kochanek z piekła rodem</title>
    <format>EPUB</format>
    <security>WM</security>
    <price>22.90</price>
    <isbn>978-83-7551-356-1</isbn>
    <coverId>145500</coverId>
    <authors>Sabrina Jeffries</authors>
    <url>http://virtualo.pl/kochanek_piekla_rodem/i129027/</url>
    <description>
      <p>Lord Jarret Sharpe, nałogowy karciarz i kobieciarz, skłonny jest raczej  poprowadzić rodzinny browar, niż się ożenić. A taki bezlitosny warunek  uzyskania dostępu do rodzinnego majątku stawia przed nim i jego  rodzeństwem babka. Wszyscy muszą w ciągu roku zmienić swój stan cywilny.  Jeśli lordowi Jarretowi uda się zwiększyć dochody nieźle prosperującego  browaru  on i rodzeństwo będą mieli utrzymanie, nawet jeśli nie zdołają  spełnić warunku babki. Nieoczekiwanie pojawia się intrygująca panna  Lake. Potrzebuje pomocy w sprzedaży doskonałego piwa, które według jej  receptury robione jest w małym i podupadającym browarze jej brata. Musi  ratować browar sama, bo brat jest alkoholikiem. Zlekceważona, postanawia  zagrać na słabości hazardzisty. Proponuje grę w karty o dość niezwykłą  stawkę. Jeśli lord Jarret przegra, będzie musiał zgodzić się na wspólne  przedsięwzięcie, jeśli zaś wygra, ona ... ofiaruje mu swoje ciało. Czy  człowiekowi honoru wolno jest przyjąć taki zakład? Panna stawia na szali  bezcenną reputację, a więc całe swoje życie. Jakie okoliczności kryją  się za tak desperackim krokiem? I jakiego jeszcze piwa nawarzą namiętni  gracze?</p>
    </description>
    <descriptionShort>Książka z cyklu Diablęta z Hallstead Hall 
Lord Jarret Sharpe, nałogowy karciarz i kobieciarz, skłonny jest raczej poprowadzić rodzinny browar, niż się ożenić.....</descriptionShort>
    <rating>0</rating>
  </product>
  <product>
    <title>Kościół pod wezwaniem Przemienienia Pańskiego w Aleksandrowie Kujawskim Wybrane aspekty z historii świątyni i jej wyposażenia</title>
    <format>PDF</format>
    <security>WM</security>
    <price>18.00</price>
    <isbn>978-83-272-3944-0</isbn>
    <coverId>131375</coverId>
    <authors>Robert Stodolny</authors>
    <url>http://virtualo.pl/kosciol_pod_wezwaniem_przemienienia_panskiego_w/i129028/</url>
    <description>
      <p>Niniejsze<span> </span>opracowanie<span> </span>jest<span> </span>poświęcone<span> </span>wybranym elementom historii kościoła w Aleksandrowie Kujawskim oraz zgromadzonym w nim dziełom sztuki. Historia budowy i rozbudowy kościoła pokazuje, jak w soczewce, losy lokalnej społeczności starającej się budować własną tożsamość nawet w niesprzyjających czasach rozbiorów.</p>
      <p>Autor zwraca uwagę na cenne dzieła sztuki, których znajomość warta jest szerszego zainteresowania. Należą do nich barokowy obraz Chrystusa ukrzyżowanego, ufundowany przez prymasa Michała S. Radziejowskiego do kaplicy św. Karola Boromeusza w seminarium księży misjonarzy w Łowiczu ok. 1695-1700 r. oraz<span> </span>relief „Ostatnia wieczerza” Wacława Bębnowskiego.</p>
      <p>Miłośników zagadek w stylu „Kodu Leonarda da Vinci” Dana Browna, zaskoczyć może obecność w Aleksandrowskim kościele płaskorzeźby „Ostatnia Wieczerza”, będącej swoistą polemiką artystyczną z obrazem Leonarda. Autorem reliefu jest utalentowany artysta Wacław Bębnowski (1865-1945). Dzieło to, tak jak i inne prace tego artysty wykonane do tego kościoła, dotychczas pozostawało niezauważone</p>
      <p>Całość osadzona jest w kontekście historycznym. Autor podkreśla szerokie zaangażowanie w powstanie i rozwój świątyni miejscowej społeczności oraz<span> </span>rodziny Trojanowskich - miejscowych ziemian.</p>
    </description>
    <descriptionShort>Autor opisuje historię świątyni oraz zwraca uwagę na cenne dzieła sztuki. Należą do nich: obraz Chrystusa ukrzyżowanego, ufundowany przez prymasa M. Radziejowskiego do kaplicy w Łowiczu ok. 1695-1700 r. oraz  relief „Ostatnia ...</descriptionShort>
    <rating>0</rating>
  </product>
  <product>
    <title>Z floty carskiej do polskiej</title>
    <format>EPUB</format>
    <security>WM</security>
    <price>40.40</price>
    <isbn>978-83-244-0301-1</isbn>
    <coverId>143133</coverId>
    <authors>Mamert Stankiewicz</authors>
    <url>http://virtualo.pl/floty_carskiej_do_polskiej/i129029/</url>
    <description>
      <p>Dziennik Mamerta Stankiewicza powstawał przez prawie dwadzieścia lat  i jest zapisem bogatego w wydarzenia życia kapitana, a także niezwykłym  dokumentem obrazującym codzienność ludzi morza. Pochodzący z polskiej  szlachty kresowej, Mamert Stankiewicz zdobywał wykształcenie w szkołach  morskich carskiej Rosji, w czasie I wojny światowej walczył we Flocie  Bałtyckiej, a później w armii Kołczaka na Syberii. Od chwili powrotu do  ojczyzny poświęcił się tworzeniu polskiej floty handlowej. Odznaczono go  Krzyżem Orderu Virtuti Militari.</p>
    </description>
    <descriptionShort>Dziennik Mamerta Stankiewicza powstawał przez prawie dwadzieścia lat</descriptionShort>
    <rating>0</rating>
  </product>
</products>
