<?xml version="1.0" encoding="iso-8859-2"?>
<!--
	    Dane z dnia: sob, 21 wrz 2013, 01:07:24 CEST

!!!!!!!!!!!!!!!!!!!!!!!!!!!!!!!!!!!!!!!!!!!!!!!!!!!!!!!!!!!!!!!!!!!!!!!!!!!!!!!
 Ze wzglêdu na wielko¶æ pliku XML, proszê o ¶ci±ganie wersji produkty-dlabystrzakow.xml.zip
!!!!!!!!!!!!!!!!!!!!!!!!!!!!!!!!!!!!!!!!!!!!!!!!!!!!!!!!!!!!!!!!!!!!!!!!!!!!!!!

            Je¶li bêdziesz sprzedawa³ ksi±¿ki w PP, to u¿yj pola <status>:

		0 - niedostepna
		1 - dostepna
		2 - w przygotowaniu
		5 - druk na ¿±danie
		7 - przedsprzedaz
	    oraz <cena>, <cenadetaliczna> (ceny takie jak na stronach GW Helion : moga zawierac znizki itp.)

	    dla ksiegarni internetowych (wspolpraca z dzialem handlowym, ehelion) u¿yj pola <status2>:

    		1 - dostêpna
		2 - dostêpna w ma³ej ilo¶ci
		3 - chwilowo niedostêpna
		4 - niedostêpna
		5 - POD
		6 - w przygotowaniu
		7 - w przedsprzeda¿y
            oraz pola <ksiegarnie_nieinter> gdzie znajduja sie wszystkie dane odnosnie ceny netto, brutto, stawka VAT

		<typ>:
			1 - ksiazka
			2 - ebook
			3 - audiobook mp3
			4 - audiocd mp3

		<marka>:
			1 - helion
			2 - onepress
			3 - editio
			4 - sensus
			5 - septem
			6 - bezdroza
			8 - podrecznik
			11 - bezdro¿a obce

Zmiany:
09.02.2011 @MJJ dolo¿enie elementu <typ>
15.06.2011 @MJJ dodanie pliku lista2-statusy.xml z samymi statusami, cenami
21.12.2011 @TKr seolinki, zagregowane formaty ebooków
23.01.2012 @TKr info o promocjach, lista promocji serwis.pl/xml/lista-promocje.cgi
15.06.2012 @TKr dodane info o audiobookach
29.08.2012 @TKr dodane md5 jako wßka¼nik zmiany informacji w ksi±¿ce

		Kontakt: Michal Jêczalik <michal.jeczalik@helion.pl>
-->
<details>
  <lista baza="dlabystrzakow">
    <ksiazka ident="AKCIAZ">
      <isbn>978-83-246-1626-8</isbn>
      <ean>9788324616268</ean>
      <ident>AKCIAZ</ident>
      <tytul language="polski">Aktywna ci±¿a dla bystrzaków</tytul>
      <tytul language="oryginal">Fit Pregnancy for Dummies</tytul>
      <link>http://dlabystrzakow.pl/ksiazki/aktywna-ciaza-dla-bystrzakow-catherine-cram-tere-stouffer-drenth,akciaz.htm</link>
      <autor>Catherine Cram, Tere Stouffer Drenth</autor>
      <tlumacz>Anna Owsiak, Izabela Szybilska-Fiedorowicz</tlumacz>
      <status>0</status>
      <cena>34.90</cena>
      <cenadetaliczna>34.90</cenadetaliczna>
      <znizka>0.00</znizka>
      <marka>5</marka>
      <nazadanie>0</nazadanie>
      <format>180x235</format>
      <typ>1</typ>
      <oprawa>miêkka</oprawa>
      <wydawca/>
      <liczbastron>384</liczbastron>
      <datawydania>2008-05-14</datawydania>
      <online>http://pdf.helion.pl/akciaz/akciaz-1.pdf</online>
      <okladka>http://dlabystrzakow.pl/okladki/326x466/akciaz.jpg</okladka>
      <top>18</top>
      <bestseller>1</bestseller>
      <nowosc>0</nowosc>
      <powiazane>
        <ident_powiazany>ELEBYS</ident_powiazany>
        <ident_powiazany>HOASTR</ident_powiazany>
        <ident_powiazany>JOGA</ident_powiazany>
        <ident_powiazany>JOGABY</ident_powiazany>
        <ident_powiazany>KUCHBE</ident_powiazany>
        <ident_powiazany>MIGREN</ident_powiazany>
        <ident_powiazany>NADCBY</ident_powiazany>
        <ident_powiazany>OGROD</ident_powiazany>
        <ident_powiazany>RZUPAL</ident_powiazany>
        <ident_powiazany>SLEEP</ident_powiazany>
        <ident_powiazany>WYPUBO</ident_powiazany>
      </powiazane>
      <serietematyczne>
        <seriatematyczna id="14">¯ycie rodzinne</seriatematyczna>
        <seriatematyczna id="12">Zdrowie i uroda</seriatematyczna>
      </serietematyczne>
      <ksiegarnie_nieinter>
        <waga>0.58</waga>
        <status2>3</status2>
        <cena_netto>33.24</cena_netto>
        <cena_brutto>34.9</cena_brutto>
        <vat>1.66</vat>
        <vat_procent>5</vat_procent>
      </ksiegarnie_nieinter>
      <opis><![CDATA[<div align="center"><h4><b> Ci±¿a w stylu fitness</b></h4></div> 

<p>Oswoi³a¶ siê ju¿ z my¶l±, ¿e jeste¶ w ci±¿y? Niew±tpliwym plusem jest to, ¿e ludzie w autobusie ustêpuj± Ci miejsca i masz prawo podchodziæ do okienek w urzêdach bez kolejki. Minusem jest za¶ to, ¿e stare ubrania przestaj± na Ciebie pasowaæ. Pewnie ju¿ zastanawiasz siê, jak bêdziesz wygl±daæ za kilka miesiêcy? Fakt, ¿e w Twoim brzuchu rozwija siê ma³y cz³owiek, nie oznacza, ¿e musisz zachowywaæ siê niczym szklany, nieruchomy inkubator. Mo¿esz uprawiaæ sport i zachowaæ ¶wietn± formê a¿ do chwili rozwi±zania. Wa¿ne tylko, by¶ robi³a to pod okiem specjalistów - takich jak autorzy Aktywnej ci±¿y dla bystrzaków.</p>

<p>Joga, p³ywanie, trening si³owy i aerobik - ruch sprawi, ¿e okres ci±¿y stanie siê nie tylko czasem oczekiwania na potomka, ale równie¿ przygotuje Ciê fizycznie na jego przyj¶cie. Znajdziesz tu æwiczenia dla siebie - bez wzglêdu na to, czy wcze¶niej aktywnie uprawia³a¶ sport, czy by³a¶ raczej dziewczyn± "kanapow±". Dowiedz siê, które z æwiczeñ s± dla Ciebie wskazane, a jakich powinna¶ unikaæ. Poczytaj o tym, jak prawid³owo od¿ywiaæ siê podczas ci±¿y i po rozwi±zaniu oraz jak zachowaæ zdrowie - zarówno fizyczne, jak i psychiczne - w obliczu wa¿nej zmiany w Twoim ¿yciu.</p>

<ul>
<li>Bezpieczny program treningowy na czas ci±¿y.</li>
<li>Uelastycznianie cia³a, poprawianie kr±¿enia oraz zdrowy sen.</li>
<li>Metody kontroli prawid³owego przyrostu masy cia³a. </li>
<li>Przygotowanie cia³a do akcji porodowej oraz porodu.</li>
<li>Szczegó³owe opisy æwiczeñ na kolejne etapy ci±¿y.</li>
<li>Sposoby anga¿owania rodziny i przyjació³ w swój bieg po kondycjê.</li>
</ul>]]></opis>
      <md5>0017a7de66d8d39855ce8d12e55ec2e9</md5>
    </ksiazka>
  </lista>
</details>
