<?xml version="1.0" encoding="utf-8"?>
<catalog>
  <item>
    <id>366624</id>
    <time>2009-05-03 00:50:32</time>
    <title><![CDATA[ABC Importera. Bariery techniczne w imporcie]]></title>
    <producer_ident>978-83-61744-07-8</producer_ident>
    <describe_short><![CDATA[<p>Obowiązki importera przy przywozie sześciu typów towarów.</p>]]></describe_short>
    <describe_long><![CDATA[<p>Obowiązki importera przy przywozie następujących towar&oacute;w:</p>
<ul>
<li>zabawki </li>
<li>towary paczkowane, </li>
<li>przyrządy pomiarowe, </li>
<li>fluorowane gazy cieplarniane, </li>
<li>niebezpieczne chemikalia, </li>
<li>wyroby medyczne. </li>
</ul>
<p>&nbsp;</p>]]></describe_long>
    <status>1</status>
    <price>29.90</price>
    <price_promo>0.00</price_promo>
    <authors_0>Bogusław Śledź</authors_0>
    <covers_0>http://www.escapemagazine.pl/uploads/covers/pmsIKtQdAJ_150.jpg</covers_0>
    <title_sub/>
    <categories_0>Tradycyjny</categories_0>
    <producer_id>1</producer_id>
    <producer_producer>Escape Magazine</producer_producer>
    <url>http://www.escapemagazine.pl/366624-abc-importera-bariery</url>
  </item>
</catalog>
